AriBasicCalculator/__init__.py
aribasiccalculator-0.0.1.dist-info/LICENSE.txt
aribasiccalculator-0.0.1.dist-info/METADATA
aribasiccalculator-0.0.1.dist-info/WHEEL
aribasiccalculator-0.0.1.dist-info/top_level.txt
aribasiccalculator-0.0.1.dist-info/RECORD
